royalherald/__init__.py
royalherald/broadcast.py
royalherald/config.py
royalherald/errors.py
royalherald/link.py
royalherald/package.py
royalherald/request.py
royalherald/response.py
royalherald/server.py
royalherald-5.1b2.dist-info/METADATA
royalherald-5.1b2.dist-info/WHEEL
royalherald-5.1b2.dist-info/top_level.txt
royalherald-5.1b2.dist-info/RECORD
