Metadata-Version: 2.1
Name: royalherald
Version: 5.1b2
Summary: A websocket communication protocol
Home-page: https://github.com/Steffo99/royalherald
Author: Stefano Pigozzi
Author-email: ste.pigozzi@gmail.com
License: UNKNOWN
Platform: UNKNOWN
Classifier: Development Status :: 4 - Beta
Classifier: Operating System :: OS Independent
Classifier: Programming Language :: Python :: 3.7
Classifier: License :: OSI Approved :: MIT License
Requires-Python: >=3.7
Requires-Dist: websockets (>=8.0)
